{
  "project_info": {
    "project_number": "635693877680",
    "project_id": "book-lover-8bffc",
    "storage_bucket": "book-lover-8bffc.appspot.com"
  },
  "client": [
    {
      "client_info": {
        "mobilesdk_app_id": "1:635693877680:android:70cdc2552396fcd8c46e75",
        "android_client_info": {
          "package_name": "com.example.bookloveer"
        }
      },
      "oauth_client": [
        {
          "client_id": "635693877680-jqnp8rt1ud7o9bu3vnnclccsdj3ncrpq.apps.googleusercontent.com",
          "client_type": 3
        }
      ],
      "api_key": [
        {
          "current_key": "AIzaSyDEVyvKqkooBTBjHwAnw1NajIzP9ZcljaM"
        }
      ],
      "services": {
        "appinvite_service": {
          "other_platform_oauth_client": [
            {
              "client_id": "635693877680-jqnp8rt1ud7o9bu3vnnclccsdj3ncrpq.apps.googleusercontent.com",
              "client_type": 3
            }
          ]
        }
      }
    }
  ],
  "configuration_version": "1"
}